arlunio/__init__.py
arlunio/_version.py
arlunio/color.py
arlunio/image.py
arlunio/imp.py
arlunio/mask.py
arlunio/math.py
arlunio/pattern.py
arlunio/shape.py
arlunio/testing.py
arlunio/cli/__init__.py
arlunio/cli/__main__.py
arlunio/cli/_interface.py
arlunio/cli/repl.py
arlunio/cli/tutorial.py
arlunio/doc/__init__.py
arlunio/doc/image.py
arlunio/doc/notebook.py
arlunio/raytrace/__init__.py
arlunio/raytrace/camera.py
arlunio/raytrace/data.py
arlunio/raytrace/material.py
arlunio/raytrace/object.py
arlunio/raytrace/render.py
arlunio/tutorial/__init__.py
arlunio/tutorial/index.ipynb
arlunio/tutorial/getstarted/first-image.ipynb
arlunio/tutorial/getstarted/index.ipynb
arlunio/tutorial/getstarted/resources/first-image-soln-01.py
arlunio/tutorial/getstarted/resources/sunny-day.png
arlunio/tutorial/getstarted/resources/sunset.png
arlunio-0.10.0.dist-info/LICENSE
arlunio-0.10.0.dist-info/METADATA
arlunio-0.10.0.dist-info/WHEEL
arlunio-0.10.0.dist-info/entry_points.txt
arlunio-0.10.0.dist-info/top_level.txt
arlunio-0.10.0.dist-info/RECORD
