Metadata-Version: 2.1
Name: arlunio
Version: 0.10.0
Summary: Drawing and animating with a blend of Python and mathematics.
Home-page: UNKNOWN
Author: Swyddfa Developers
Author-email: swyddfa.dev@gmail.com
License: MIT
Project-URL: Documentation, https://www.arlun.io/docs/
Project-URL: Source, https://github.com/swyddfa/arlunio
Project-URL: Tracker, https://github.com/swyddfa/arlunio/issues
Platform: UNKNOWN
Classifier: Development Status :: 3 - Alpha
Classifier: License :: OSI Approved :: MIT License
Classifier: Programming Language :: Python
Classifier: Programming Language :: Python :: 3
Classifier: Programming Language :: Python :: 3.6
Classifier: Programming Language :: Python :: 3.7
Classifier: Programming Language :: Python :: 3.8
Classifier: Programming Language :: Python :: Implementation :: CPython
Classifier: Topic :: Multimedia :: Graphics
Requires-Python: >=3.6
Requires-Dist: attrs
Requires-Dist: appdirs
Requires-Dist: ipython
Requires-Dist: numpy
Requires-Dist: Pillow (>=6.1.0)
Provides-Extra: all
Requires-Dist: hypothesis ; extra == 'all'
Requires-Dist: jupyterlab ; extra == 'all'
Requires-Dist: nbformat ; extra == 'all'
Requires-Dist: sphinx ; extra == 'all'
Provides-Extra: dev
Requires-Dist: black ; extra == 'dev'
Requires-Dist: flake8 ; extra == 'dev'
Requires-Dist: hypothesis ; extra == 'dev'
Requires-Dist: jupyterlab ; extra == 'dev'
Requires-Dist: pre-commit ; extra == 'dev'
Requires-Dist: pytest ; extra == 'dev'
Requires-Dist: pytest-cov ; extra == 'dev'
Requires-Dist: sphinx-autobuild ; extra == 'dev'
Requires-Dist: sphinx-rtd-theme ; extra == 'dev'
Requires-Dist: sphobjinv ; extra == 'dev'
Requires-Dist: towncrier ; extra == 'dev'
Requires-Dist: tox ; extra == 'dev'
Provides-Extra: doc
Requires-Dist: sphinx ; extra == 'doc'
Requires-Dist: nbformat ; extra == 'doc'
Provides-Extra: examples
Requires-Dist: jupyterlab ; extra == 'examples'
Provides-Extra: testing
Requires-Dist: hypothesis ; extra == 'testing'
